{
    "name": "glCDMtoOnDemand_Small",
    "properties": {
        "activities": [
            {
                "name": "Create GL External Table",
                "type": "SqlServerStoredProcedure",
                "dependsOn": [],
                "policy": {
                    "timeout": "7.00:00:00",
                    "retry": 0,
                    "retryIntervalInSeconds": 30,
                    "secureOutput": false,
                    "secureInput": false
                },
                "userProperties": [],
                "typeProperties": {
                    "storedProcedureName": "[dbo].[usp_GeneralJournal_ext]",
                    "storedProcedureParameters": {
                        "CDMLocation": {
                            "value": {
                                "value": "@pipeline().parameters.CDM_Folder_Path",
                                "type": "Expression"
                            },
                            "type": "String"
                        },
                        "Container": {
                            "value": {
                                "value": "@pipeline().parameters.CDM_Container",
                                "type": "Expression"
                            },
                            "type": "String"
                        },
                        "StorageAcc": {
                            "value": {
                                "value": "@pipeline().parameters.StorageAccount",
                                "type": "Expression"
                            },
                            "type": "String"
                        }
                    }
                },
                "linkedServiceName": {
                    "referenceName": "SQLOnDemand",
                    "type": "LinkedServiceReference"
                }
            }
        ],
        "parameters": {
            "CDM_Folder_Path": {
                "type": "string",
                "defaultValue": "gldata/glsmalloutput/GeneralJournal/<currentUTCDate>/"
            },
            "CDM_Container": {
                "type": "string",
                "defaultValue": "models"
            },
            "StorageAccount": {
                "type": "string",
                "defaultValue": "<SyanpseDefaultADLSName>"
            }
        },
        "annotations": [],
        "lastPublishTime": "2021-06-07T12:44:49Z"
    },
    "type": "Microsoft.Synapse/workspaces/pipelines"
}